calculator_service/__init__.py
calculator_service/server.py
calculator_service-0.1.0.dist-info/METADATA
calculator_service-0.1.0.dist-info/WHEEL
calculator_service-0.1.0.dist-info/entry_points.txt
calculator_service-0.1.0.dist-info/licenses/LICENSE
calculator_service-0.1.0.dist-info/RECORD
