Metadata-Version: 2.4
Name: calculator-service
Version: 0.1.0
Summary: A simple FastMCP calculator service
License: MIT License
License-File: LICENSE
Requires-Python: >=3.11
Requires-Dist: build
Requires-Dist: fastmcp>=0.1.0
Requires-Dist: mcp[cli]
Requires-Dist: twine
